[
  {
    "_id": "699971a6735ab9ada9b9aacd",
    "openingHours": [
      {
        "day": "monday",
        "open": "10:34",
        "close": "23:59",
        "closed": false
      },
      {
        "day": "tuesday",
        "open": "06:23",
        "close": "17:26",
        "closed": false
      },
      {
        "day": "wednesday",
        "open": "20:54",
        "close": "21:52",
        "closed": false
      },
      {
        "day": "thursday",
        "open": "14:28",
        "close": "02:40",
        "closed": false
      },
      {
        "day": "friday",
        "open": "08:02",
        "close": "01:13",
        "closed": true
      },
      {
        "day": "saturday",
        "open": "05:24",
        "close": "00:34",
        "closed": true
      },
      {
        "day": "sunday",
        "open": "00:05",
        "close": "18:13",
        "closed": true
      }
    ],
    "gallery": [
      "/api/uploads/a8c66290-c418-4695-9377-fc5f539b0d9f.jpg",
      "/api/uploads/ba84a47e-2bd3-4cb2-8cdb-4a02a43e84dc.jpg",
      "/api/uploads/e3ead165-e88e-4781-ba7c-5cfb9815c00e.jpg",
      "/api/uploads/c49819f6-a015-423b-9847-c8e229239216.jpg",
      "/api/uploads/f0780099-0ccb-45cb-bf36-a590a56bc14b.jpg",
      "/api/uploads/4c0ad515-cb06-40e2-b13b-8f7b43ab09c8.jpg"
    ],
    "specialOpeningHours": [
      {
        "dateFrom": "2026-04-06T00:00:00.000Z",
        "dateTo": "2026-04-09T00:00:00.000Z",
        "closed": true,
        "note": "TEST OBDOBÍ Voluptate quos atque libero omnis fugiat odit commodi autem sit veniam reprehenderit minus"
      },
      {
        "date": "1993-06-27T00:00:00.000Z",
        "closed": true,
        "note": "Et est labore dolore unde dolores sit veniam eos adipisicing ea quos"
      },
      {
        "date": "2017-10-15T00:00:00.000Z",
        "open": "15:33",
        "close": "21:10",
        "closed": false,
        "note": "Rem ut in est quo voluptas sed voluptatem sed voluptatem Optio"
      }
    ],
    "createdAt": "2026-02-21T08:49:42.621Z",
    "updatedAt": "2026-04-10T08:20:38.528Z",
    "__v": 14,
    "facebook": "https://www.pijovaverehy.co.uk",
    "instagram": "https://www.cowexavak.org.uk",
    "mainImage": "",
    "shortText": "VAŠE CESTA K ZÁŽITKŮM",
    "text": "<p style=\"text-align: center;\">OC Plaza Liberec stojí v&nbsp;atraktivní lokalitě přímo v&nbsp;historickém jádru města. Svojí pasáží se napojuje na pěší zónu vedoucí centrem Liberce. Zastávky MHD jsou umístěny v&nbsp;Palachově ulici, bezprostředně vedle vstupu do obchodního centra. Díky unikátnímu architektonickému řešení vznikly pasáže, které spojují náměstí E. Beneše s&nbsp;Palachovou ulicí. Součástí centra je také kancelářská věž a bytové prostory.</p><p></p><h2 style=\"text-align: center;\"><strong>Důležité kontakty</strong><br><strong>a otevírací doba centra (bude nová komponenta)</strong></h2><p>Kontaktní email<br><br>Veronika Randýsková<br>+420 777 777 777<br><a target=\"_blank\" rel=\"noopener noreferrer\" class=\"text-plaza-600 underline hover:text-plaza-800\" href=\"https://randyskova@ocplazaliberec.cz\"><u>m.bily@ocplazaliberec.cz</u></a></p><p></p><p>Velín ostrahy<br><br>Michal Bílý<br>+420 777 777 777<br><a target=\"_blank\" rel=\"noopener noreferrer nofollow\" class=\"text-plaza-600 underline hover:text-plaza-800\" href=\"mailto:m.bily@ocplazaliberec.cz\"><u>m.bily@ocplazaliberec.cz</u></a></p><p></p><p>Technická správa budovy<br><br>Michal Bílý<br>+420 777 777 777<br><a target=\"_blank\" rel=\"noopener noreferrer nofollow\" class=\"text-plaza-600 underline hover:text-plaza-800\" href=\"mailto:m.bily@ocplazaliberec.cz\"><u>m.bily@ocplazaliberec.cz</u></a></p>",
    "title": "Plaza spojuje",
    "staticAroundMap": "/api/uploads/01cedaba-1a0e-48f4-bfd8-2b604fa7167a.svg",
    "parkingContent": "<ul><li><p>490 parkovacích míst</p></li><li><p>3 patra podzemního parkoviště</p></li><li><p>Dobíjecí místa pro elektromobily</p></li><li><p>Vyhrazená místa pro invalidy</p></li><li><p>Maximální výška automobilu 2m</p></li><li><p>Otevřeno 24/7</p></li></ul>",
    "parkingImage": "",
    "parkingOtherInfo": "<p><strong>Ceník parkovného</strong></p><ul><li><p>1.&nbsp;hodina zdarma</p></li><li><p>Každá další započatá hodina je zpoplatněna částkou 60&nbsp;Kč/hodina.</p></li><li><p>O víkendech a státních svátcích je parkování prvních 5 hodin&nbsp;ZDARMA.</p></li><li><p>Při opakovaném vjezdu&nbsp;do 1. hodiny od výjezdu z parkoviště se celková parkovací doba sčítá!</p></li></ul>"
  }
]